idealab_tools/__init__.py
idealab_tools/add_system_path.py
idealab_tools/copyright_adder.py
idealab_tools/decorators.py
idealab_tools/findmodules.py
idealab_tools/iterable.py
idealab_tools/lift_drag_coeff.py
idealab_tools/makemovie.py
idealab_tools/matplotlib_tools.py
idealab_tools/plot_tris.py
idealab_tools/propertyeditor.py
idealab_tools/pyuac.py
idealab_tools/setup_tools.py
idealab_tools/text_to_polygons.py
idealab_tools/units.py
idealab_tools/virtual_structure.py
idealab_tools/data_exchange/__init__.py
idealab_tools/data_exchange/csv.py
idealab_tools/data_exchange/dat.py
idealab_tools/data_exchange/generic_data.py
idealab_tools/data_exchange/octave_dat.py
idealab_tools/geometry/__init__.py
idealab_tools/geometry/tetrahedron.py
idealab_tools/geometry/triangle.py
idealab_tools/kinematics/__init__.py
idealab_tools/kinematics/kinematics.py
idealab_tools/mechanics/__init__.py
idealab_tools/mechanics/analytical_beam.py
idealab_tools/mechanics/analytical_plate.py
idealab_tools/mechanics/analytical_plate_point_load.py
idealab_tools/mechanics/beam_bending.py
idealab_tools/mechanics/functions.py
idealab_tools/multiprocessing/__init__.py
idealab_tools/multiprocessing/process_manager.py
idealab_tools-0.0.27.dist-info/METADATA
idealab_tools-0.0.27.dist-info/WHEEL
idealab_tools-0.0.27.dist-info/top_level.txt
idealab_tools-0.0.27.dist-info/RECORD
