Metadata-Version: 2.4
Name: idealab_tools
Version: 0.0.27
Summary: Tools developed by the IDEAlab.
Home-page: https://github.com/idealabasu/code_idealab_tools.git
Author: Dan Aukes
Author-email: danaukes@danaukes.com
License: MIT
Classifier: Programming Language :: Python
Classifier: Programming Language :: Python :: 3
Requires-Dist: imageio
Dynamic: author
Dynamic: author-email
Dynamic: classifier
Dynamic: home-page
Dynamic: license
Dynamic: requires-dist
Dynamic: summary
